rpa_hypercoe_log/rpa_hypercoe_log.py
rpa_hypercoe_log-0.0.3.dist-info/LICENCE
rpa_hypercoe_log-0.0.3.dist-info/METADATA
rpa_hypercoe_log-0.0.3.dist-info/WHEEL
rpa_hypercoe_log-0.0.3.dist-info/top_level.txt
rpa_hypercoe_log-0.0.3.dist-info/RECORD
