Metadata-Version: 2.1
Name: rpa-hypercoe-log
Version: 0.0.3
Summary: Repositorio para a utilização da API de Log do HyperCoe
Home-page: UNKNOWN
Author: Joao Buso
Author-email: developer@hypercoe.com
License: MIT License
Keywords: rpa hypercoe log tria software
Platform: UNKNOWN
Requires-Dist: requests
